torchhandle/__init__.py
torchhandle/utils/LoggingRedirect.py
torchhandle/utils/ObjectDict.py
torchhandle/utils/__init__.py
torchhandle/utils/dev.py
torchhandle/utils/utils.py
torchhandle/workflow/BaseContext.py
torchhandle/workflow/FP16Context.py
torchhandle/workflow/Metric.py
torchhandle/workflow/Session.py
torchhandle/workflow/__init__.py
torchhandle-1.0.2209.1.dist-info/LICENSE
torchhandle-1.0.2209.1.dist-info/METADATA
torchhandle-1.0.2209.1.dist-info/WHEEL
torchhandle-1.0.2209.1.dist-info/top_level.txt
torchhandle-1.0.2209.1.dist-info/RECORD
