Metadata-Version: 2.1
Name: torchhandle
Version: 1.0.2209.1
Summary: TorchHandle makes your PyTorch development more efficient and make you use PyTorch more comfortable
Home-page: https://github.com/deephub-ai/torch-handle
Author: Hengtao Tantai
Author-email: deephub.ai@gmail.com
License: GPLv3
Keywords: PyTorch,Pipeline,Machine Learning,Distributed Computing,Deep Learning,Reinforcement Learning,Computer Vision,Natural Language Processing,Recommendation Systems
Platform: UNKNOWN
Classifier: Environment :: Console
Classifier: Natural Language :: English
Classifier: Development Status :: 4 - Beta
Classifier: Operating System :: OS Independent
Classifier: License :: OSI Approved :: GNU General Public License v3 (GPLv3)
Classifier: Intended Audience :: Developers
Classifier: Intended Audience :: Science/Research
Classifier: Topic :: Scientific/Engineering :: Artificial Intelligence
Classifier: Topic :: Scientific/Engineering :: Image Recognition
Classifier: Topic :: Scientific/Engineering :: Information Analysis
Classifier: Programming Language :: Python
Classifier: Programming Language :: Python :: 3.6
Classifier: Programming Language :: Python :: 3.7
Classifier: Programming Language :: Python :: 3.8
Classifier: Programming Language :: Python :: 3.9
Requires-Python: >=3.6.0
Requires-Dist: torch
Requires-Dist: tqdm
Requires-Dist: matplotlib
